{
    "angles" : [
        178.5719399269345,
        13.284019697461048,
        -3.055351195517734
    ],
    "landmarks" : {
        "LeftBrowMiddle_down" : {
            "x" : 527.0209350585938,
            "y" : 570.03125
        },
        "Ridge2" : {
            "x" : 456.9397888183594,
            "y" : 661.2545166015625
        },
        "LeftEyeInnerEyeCorner" : {
            "x" : 476.8558654785156,
            "y" : 610.830810546875
        },
        "MouthRight_down_2" : {
            "x" : 380.3865356445312,
            "y" : 882.9846801757812
        },
        "MouthRight_corner" : {
            "x" : 340.119140625,
            "y" : 794.6962280273438
        },
        "BaseLeft" : {
            "x" : 483.8043518066406,
            "y" : 708.3624267578125
        },
        "RightBrowMiddle_down" : {
            "x" : 353.4945068359375,
            "y" : 567.343505859375
        },
        "RightBrowOuter_down" : {
            "x" : 302.1512451171875,
            "y" : 578.7557373046875
        },
        "CheekLeft1" : {
            "x" : 230.4385681152344,
            "y" : 665.649658203125
        },
        "CheekRight1" : {
            "x" : 554.4241333007812,
            "y" : 673.4847412109375
        },
        "BaseCenterRight" : {
            "x" : 420.7642211914062,
            "y" : 712.4451293945312
        },
        "LeftEyeLowerOuter" : {
            "x" : 509.4368896484375,
            "y" : 615.788818359375
        },
        "BaseRight" : {
            "x" : 394.15869140625,
            "y" : 708.1175537109375
        },
        "CheekRight2" : {
            "x" : 552.652587890625,
            "y" : 723.4901123046875
        },
        "AlaLeft2" : {
            "x" : 481.7909240722656,
            "y" : 696.3329467773438
        },
        "LeftEyeUpperInner" : {
            "x" : 491.6268615722656,
            "y" : 608.4964599609375
        },
        "RightEyeInnerEyeCorner" : {
            "x" : 388.7702026367188,
            "y" : 607.1134643554688
        },
        "LeftEyeUpperOuter" : {
            "x" : 510.9990844726562,
            "y" : 609.8771362304688
        },
        "BaseCenter" : {
            "x" : 449.5211181640625,
            "y" : 720.7816162109375
        },
        "RightEyeLowerOuter" : {
            "x" : 344.4403686523438,
            "y" : 607.6957397460938
        },
        "MouthLeft_down_1" : {
            "x" : 482.187744140625,
            "y" : 838.5849609375
        },
        "MouthInner_down" : {
            "x" : 431.6489868164062,
            "y" : 864.9967041015625
        },
        "RightEyeOuterEyeCorner" : {
            "x" : 324.7142028808594,
            "y" : 608.81494140625
        },
        "RightBrowInner_down" : {
            "x" : 405.9695434570312,
            "y" : 570.4884033203125
        },
        "CheekLeft4" : {
            "x" : 251.1339416503906,
            "y" : 833.2564697265625
        },
        "MouthRight_philtrum" : {
            "x" : 424.5696716308594,
            "y" : 758.2994995117188
        },
        "MouthRight_down_1" : {
            "x" : 348.1682434082031,
            "y" : 842.6396484375
        },
        "LeftBrowOuter_up" : {
            "x" : 554.4073486328125,
            "y" : 570.003173828125
        },
        "CheekRight7" : {
            "x" : 455.297607421875,
            "y" : 952.249755859375
        },
        "MouthInner_up_right" : {
            "x" : 398.9058532714844,
            "y" : 776.6884765625
        },
        "LeftEyeLowerInner" : {
            "x" : 489.6730346679688,
            "y" : 612.8033447265625
        },
        "RightBrowMiddle_up" : {
            "x" : 350.9686279296875,
            "y" : 546.361572265625
        },
        "MouthLeft_down_2" : {
            "x" : 462.3851013183594,
            "y" : 877.1148681640625
        },
        "LeftBrowInner_down" : {
            "x" : 492.1664733886719,
            "y" : 567.7312622070312
        },
        "CheekLeft6" : {
            "x" : 313.2885131835938,
            "y" : 927.5751342773438
        },
        "CheekRight6" : {
            "x" : 480.1663208007812,
            "y" : 909.9136962890625
        },
        "MouthLeft_up_2" : {
            "x" : 477.044677734375,
            "y" : 764.40673828125
        },
        "RightEyePupil" : {
            "x" : 350.5491333007812,
            "y" : 606.4253540039062
        },
        "MouthCenter_lower" : {
            "x" : 426.1273498535156,
            "y" : 895.2864990234375
        },
        "CheekLeft7" : {
            "x" : 357.6257629394531,
            "y" : 963.618408203125
        },
        "ChinCenter" : {
            "x" : 413.3704528808594,
            "y" : 975.80078125
        },
        "RightBrowInner_up" : {
            "x" : 407.2249145507812,
            "y" : 549.811767578125
        },
        "MouthInner_down_left" : {
            "x" : 459.0430908203125,
            "y" : 848.693603515625
        },
        "RightEyeUpperInner" : {
            "x" : 370.8218994140625,
            "y" : 606.777587890625
        },
        "MouthLeft_corner" : {
            "x" : 484.909912109375,
            "y" : 792.6644287109375
        },
        "CheekRight" : {
            "x" : 549.1572265625,
            "y" : 624.944091796875
        },
        "CheekLeft" : {
            "x" : 236.5975036621094,
            "y" : 609.6075439453125
        },
        "BaseCenterLeft" : {
            "x" : 467.6180419921875,
            "y" : 714.8677978515625
        },
        "CheekRight4" : {
            "x" : 522.130615234375,
            "y" : 817.4947509765625
        },
        "MouthInner_down_right" : {
            "x" : 387.6909790039062,
            "y" : 854.4969482421875
        },
        "CheekLeft5" : {
            "x" : 278.7149658203125,
            "y" : 882.0240478515625
        },
        "AlaRight2" : {
            "x" : 416.3250732421875,
            "y" : 687.30615234375
        },
        "MouthLeft_philtrum" : {
            "x" : 461.6567993164062,
            "y" : 758.3735961914062
        },
        "LeftEyePupil" : {
            "x" : 499.19970703125,
            "y" : 611.8339233398438
        },
        "LeftBrowOuter_down" : {
            "x" : 553.9702758789062,
            "y" : 581.6404418945312
        },
        "MouthRight_up_2" : {
            "x" : 394.1114501953125,
            "y" : 763.6581420898438
        },
        "Ridge1" : {
            "x" : 451.3265991210938,
            "y" : 628.6419677734375
        },
        "AlaLeft1" : {
            "x" : 485.5363159179688,
            "y" : 671.7625732421875
        },
        "CheekRight5" : {
            "x" : 502.4781494140625,
            "y" : 863.9149169921875
        },
        "MouthInner_up_left" : {
            "x" : 461.76123046875,
            "y" : 776.2802124023438
        },
        "RightEyeLowerInner" : {
            "x" : 370.8218994140625,
            "y" : 606.777587890625
        },
        "MouthRight_up_1" : {
            "x" : 363.4559326171875,
            "y" : 775.4217529296875
        },
        "CheekRight3" : {
            "x" : 541.32373046875,
            "y" : 771.846923828125
        },
        "MouthLeft_up_1" : {
            "x" : 485.6354370117188,
            "y" : 776.4564208984375
        },
        "RidgeRoot" : {
            "x" : 446.3155517578125,
            "y" : 597.2625122070312
        },
        "RidgeTip" : {
            "x" : 460.9877624511719,
            "y" : 693.2742919921875
        },
        "LeftEyeOuterEyeCorner" : {
            "x" : 526.5130615234375,
            "y" : 616.3917236328125
        },
        "AlaRight1" : {
            "x" : 399.1708984375,
            "y" : 669.21337890625
        },
        "LeftBrowInner_up" : {
            "x" : 492.9707946777344,
            "y" : 552.520751953125
        },
        "LeftBrowMiddle_up" : {
            "x" : 528.9681396484375,
            "y" : 550.7825927734375
        },
        "RightBrowOuter_up" : {
            "x" : 299.6275634765625,
            "y" : 568.1087646484375
        },
        "MouthInner_up" : {
            "x" : 438.9315185546875,
            "y" : 777.45556640625
        },
        "CheekLeft2" : {
            "x" : 226.1712188720703,
            "y" : 723.6856689453125
        },
        "RightEyeUpperOuter" : {
            "x" : 344.4403686523438,
            "y" : 607.6957397460938
        },
        "MouthCenter_philtrum" : {
            "x" : 444.01953125,
            "y" : 761.8717041015625
        },
        "CheekLeft3" : {
            "x" : 233.2868347167969,
            "y" : 780.1607666015625
        }
    }
}