{
    "angles" : [
        -171.7831056867831,
        -28.244109400958195,
        8.785198914288461
    ],
    "landmarks" : {
        "LeftBrowMiddle_down" : {
            "x" : 282.0987854003906,
            "y" : 642.6159057617188
        },
        "Ridge2" : {
            "x" : 178.957275390625,
            "y" : 733.8334350585938
        },
        "LeftEyeInnerEyeCorner" : {
            "x" : 258.1243286132812,
            "y" : 666.7909545898438
        },
        "MouthRight_down_2" : {
            "x" : 211.1015319824219,
            "y" : 859.3815307617188
        },
        "MouthRight_corner" : {
            "x" : 181.8915100097656,
            "y" : 841.9541015625
        },
        "BaseLeft" : {
            "x" : 252.16259765625,
            "y" : 764.94677734375
        },
        "RightBrowMiddle_down" : {
            "x" : 143.3468933105469,
            "y" : 658.548095703125
        },
        "RightBrowOuter_down" : {
            "x" : 123.7134017944336,
            "y" : 655.3184814453125
        },
        "CheekLeft1" : {
            "x" : 141.7163543701172,
            "y" : 724.530029296875
        },
        "CheekRight1" : {
            "x" : 455.3632202148438,
            "y" : 683.5028686523438
        },
        "BaseCenterRight" : {
            "x" : 184.0198669433594,
            "y" : 784.1256713867188
        },
        "LeftEyeLowerOuter" : {
            "x" : 301.4381103515625,
            "y" : 664.73828125
        },
        "BaseRight" : {
            "x" : 170.6690979003906,
            "y" : 778.0812377929688
        },
        "CheekRight2" : {
            "x" : 462.0347900390625,
            "y" : 738.8723754882812
        },
        "AlaLeft2" : {
            "x" : 219.4746398925781,
            "y" : 753.683349609375
        },
        "LeftEyeUpperInner" : {
            "x" : 276.8901977539062,
            "y" : 665.6285400390625
        },
        "RightEyeInnerEyeCorner" : {
            "x" : 183.6760406494141,
            "y" : 671.9408569335938
        },
        "LeftEyeUpperOuter" : {
            "x" : 301.4381103515625,
            "y" : 664.73828125
        },
        "BaseCenter" : {
            "x" : 200.2403869628906,
            "y" : 789.714599609375
        },
        "RightEyeLowerOuter" : {
            "x" : 155.9852294921875,
            "y" : 679.8938598632812
        },
        "MouthLeft_down_1" : {
            "x" : 295.3204956054688,
            "y" : 833.6947631835938
        },
        "MouthInner_down" : {
            "x" : 224.7658386230469,
            "y" : 836.200927734375
        },
        "RightEyeOuterEyeCorner" : {
            "x" : 145.7429809570312,
            "y" : 678.5152587890625
        },
        "RightBrowInner_down" : {
            "x" : 166.1708984375,
            "y" : 664.416748046875
        },
        "CheekLeft4" : {
            "x" : 163.0150756835938,
            "y" : 845.027587890625
        },
        "MouthRight_philtrum" : {
            "x" : 203.9332885742188,
            "y" : 825.081298828125
        },
        "MouthRight_down_1" : {
            "x" : 192.33447265625,
            "y" : 852.6878051757812
        },
        "LeftBrowOuter_up" : {
            "x" : 339.418701171875,
            "y" : 627.081298828125
        },
        "CheekRight7" : {
            "x" : 305.3330688476562,
            "y" : 955.6981201171875
        },
        "MouthInner_up_right" : {
            "x" : 207.1847839355469,
            "y" : 838.5004272460938
        },
        "LeftEyeLowerInner" : {
            "x" : 276.8901977539062,
            "y" : 665.6285400390625
        },
        "RightBrowMiddle_up" : {
            "x" : 140.6219177246094,
            "y" : 641.732177734375
        },
        "MouthLeft_down_2" : {
            "x" : 262.5101318359375,
            "y" : 850.3382568359375
        },
        "LeftBrowInner_down" : {
            "x" : 229.1224365234375,
            "y" : 657.67529296875
        },
        "CheekLeft6" : {
            "x" : 195.1942138671875,
            "y" : 917.9508666992188
        },
        "CheekRight6" : {
            "x" : 354.7716674804688,
            "y" : 929.0848388671875
        },
        "MouthLeft_up_2" : {
            "x" : 262.5469970703125,
            "y" : 814.7535400390625
        },
        "RightEyePupil" : {
            "x" : 168.640625,
            "y" : 674.408447265625
        },
        "MouthCenter_lower" : {
            "x" : 229.7474365234375,
            "y" : 860.2515869140625
        },
        "CheekLeft7" : {
            "x" : 216.5848999023438,
            "y" : 949.9454345703125
        },
        "ChinCenter" : {
            "x" : 251.0352783203125,
            "y" : 965.7667236328125
        },
        "RightBrowInner_up" : {
            "x" : 164.1324462890625,
            "y" : 650.2027587890625
        },
        "MouthInner_down_left" : {
            "x" : 261.4560852050781,
            "y" : 825.7706298828125
        },
        "RightEyeUpperInner" : {
            "x" : 172.14013671875,
            "y" : 672.754638671875
        },
        "MouthLeft_corner" : {
            "x" : 318.2726440429688,
            "y" : 813.8270263671875
        },
        "CheekRight" : {
            "x" : 446.7515563964844,
            "y" : 630.6466064453125
        },
        "CheekLeft" : {
            "x" : 142.430908203125,
            "y" : 682.634521484375
        },
        "BaseCenterLeft" : {
            "x" : 226.0517425537109,
            "y" : 776.145263671875
        },
        "CheekRight4" : {
            "x" : 436.7844848632812,
            "y" : 845.7494506835938
        },
        "MouthInner_down_right" : {
            "x" : 207.1847839355469,
            "y" : 838.5004272460938
        },
        "CheekLeft5" : {
            "x" : 176.8872680664062,
            "y" : 882.681640625
        },
        "AlaRight2" : {
            "x" : 167.4157104492188,
            "y" : 771.8615112304688
        },
        "MouthLeft_philtrum" : {
            "x" : 237.2840270996094,
            "y" : 818.337158203125
        },
        "LeftEyePupil" : {
            "x" : 300.2185668945312,
            "y" : 664.44482421875
        },
        "LeftBrowOuter_down" : {
            "x" : 338.984130859375,
            "y" : 639.03125
        },
        "MouthRight_up_2" : {
            "x" : 194.0905456542969,
            "y" : 827.0311279296875
        },
        "Ridge1" : {
            "x" : 188.3075714111328,
            "y" : 700.4205322265625
        },
        "AlaLeft1" : {
            "x" : 247.2000885009766,
            "y" : 728.03173828125
        },
        "CheekRight5" : {
            "x" : 400.7473449707031,
            "y" : 891.5587768554688
        },
        "MouthInner_up_left" : {
            "x" : 261.4560852050781,
            "y" : 825.7706298828125
        },
        "RightEyeLowerInner" : {
            "x" : 173.6918182373047,
            "y" : 676.6885986328125
        },
        "MouthRight_up_1" : {
            "x" : 184.7922973632812,
            "y" : 833.1357421875
        },
        "CheekRight3" : {
            "x" : 459.3501586914062,
            "y" : 794.4141845703125
        },
        "MouthLeft_up_1" : {
            "x" : 292.1020202636719,
            "y" : 810.59326171875
        },
        "RidgeRoot" : {
            "x" : 196.7008972167969,
            "y" : 668.0748291015625
        },
        "RidgeTip" : {
            "x" : 171.5561370849609,
            "y" : 767.0001220703125
        },
        "LeftEyeOuterEyeCorner" : {
            "x" : 322.3950805664062,
            "y" : 662.79052734375
        },
        "AlaRight1" : {
            "x" : 164.7671203613281,
            "y" : 742.975341796875
        },
        "LeftBrowInner_up" : {
            "x" : 222.5230407714844,
            "y" : 641.658935546875
        },
        "LeftBrowMiddle_up" : {
            "x" : 279.6199340820312,
            "y" : 622.6627197265625
        },
        "RightBrowOuter_up" : {
            "x" : 122.5939331054688,
            "y" : 641.0484619140625
        },
        "MouthInner_up" : {
            "x" : 224.7658386230469,
            "y" : 836.200927734375
        },
        "CheekLeft2" : {
            "x" : 140.2685241699219,
            "y" : 767.2264404296875
        },
        "RightEyeUpperOuter" : {
            "x" : 156.1004943847656,
            "y" : 674.6663818359375
        },
        "MouthCenter_philtrum" : {
            "x" : 221.104736328125,
            "y" : 825.8443603515625
        },
        "CheekLeft3" : {
            "x" : 150.2640991210938,
            "y" : 806.9866333007812
        }
    }
}