{
    "angles" : [
        163.54391566484452,
        -21.892708346802795,
        0.9150590918398183
    ],
    "landmarks" : {
        "LeftBrowMiddle_down" : {
            "x" : 320.4834899902344,
            "y" : 515.6370849609375
        },
        "Ridge2" : {
            "x" : 200.5068969726562,
            "y" : 610.1160888671875
        },
        "LeftEyeInnerEyeCorner" : {
            "x" : 279.9203491210938,
            "y" : 582.678955078125
        },
        "MouthRight_down_2" : {
            "x" : 191.0477905273438,
            "y" : 760.979248046875
        },
        "MouthRight_corner" : {
            "x" : 170.2271728515625,
            "y" : 755.125244140625
        },
        "BaseLeft" : {
            "x" : 252.2286071777344,
            "y" : 667.3214111328125
        },
        "RightBrowMiddle_down" : {
            "x" : 161.1819458007812,
            "y" : 543.2637329101562
        },
        "RightBrowOuter_down" : {
            "x" : 144.1153717041016,
            "y" : 558.3597412109375
        },
        "CheekLeft1" : {
            "x" : 444.0723876953125,
            "y" : 638.3531494140625
        },
        "CheekRight1" : {
            "x" : 142.8567810058594,
            "y" : 646.9371948242188
        },
        "BaseCenterRight" : {
            "x" : 193.9188690185547,
            "y" : 671.405029296875
        },
        "LeftEyeLowerOuter" : {
            "x" : 325.3897705078125,
            "y" : 586.1259155273438
        },
        "BaseRight" : {
            "x" : 182.6649932861328,
            "y" : 675.2943115234375
        },
        "CheekRight2" : {
            "x" : 138.0999145507812,
            "y" : 684.927490234375
        },
        "AlaLeft2" : {
            "x" : 237.6504821777344,
            "y" : 641.8421630859375
        },
        "LeftEyeUpperInner" : {
            "x" : 297.1814575195312,
            "y" : 572.9747314453125
        },
        "RightEyeInnerEyeCorner" : {
            "x" : 204.9352416992188,
            "y" : 596.137939453125
        },
        "LeftEyeUpperOuter" : {
            "x" : 324.6464538574219,
            "y" : 570.5401611328125
        },
        "BaseCenter" : {
            "x" : 206.8415222167969,
            "y" : 671.365478515625
        },
        "RightEyeLowerOuter" : {
            "x" : 175.0923156738281,
            "y" : 609.813720703125
        },
        "MouthLeft_down_1" : {
            "x" : 259.0962524414062,
            "y" : 753.17724609375
        },
        "MouthInner_down" : {
            "x" : 204.6378936767578,
            "y" : 736.3154907226562
        },
        "RightEyeOuterEyeCorner" : {
            "x" : 161.6532897949219,
            "y" : 604.909423828125
        },
        "RightBrowInner_down" : {
            "x" : 187.02685546875,
            "y" : 538.1396484375
        },
        "CheekLeft4" : {
            "x" : 407.5498657226562,
            "y" : 793.68310546875
        },
        "MouthRight_philtrum" : {
            "x" : 189.8153076171875,
            "y" : 716.887939453125
        },
        "MouthRight_down_1" : {
            "x" : 177.9397277832031,
            "y" : 759.7594604492188
        },
        "LeftBrowOuter_up" : {
            "x" : 367.6495971679688,
            "y" : 519.2965698242188
        },
        "CheekRight7" : {
            "x" : 181.45458984375,
            "y" : 862.36572265625
        },
        "MouthInner_up_right" : {
            "x" : 190.0480041503906,
            "y" : 740.5917358398438
        },
        "LeftEyeLowerInner" : {
            "x" : 298.8662109375,
            "y" : 587.1215209960938
        },
        "RightBrowMiddle_up" : {
            "x" : 157.406982421875,
            "y" : 526.779296875
        },
        "MouthLeft_down_2" : {
            "x" : 229.9101257324219,
            "y" : 756.783447265625
        },
        "LeftBrowInner_down" : {
            "x" : 271.1734619140625,
            "y" : 522.2526245117188
        },
        "CheekLeft6" : {
            "x" : 319.7221374511719,
            "y" : 858.0342407226562
        },
        "CheekRight6" : {
            "x" : 162.9443359375,
            "y" : 832.7235107421875
        },
        "MouthLeft_up_2" : {
            "x" : 241.7374877929688,
            "y" : 720.6715087890625
        },
        "RightEyePupil" : {
            "x" : 188.7495727539062,
            "y" : 599.0670166015625
        },
        "MouthCenter_lower" : {
            "x" : 204.5068664550781,
            "y" : 761.4090576171875
        },
        "CheekLeft7" : {
            "x" : 267.608154296875,
            "y" : 873.471435546875
        },
        "ChinCenter" : {
            "x" : 213.2852478027344,
            "y" : 877.3795776367188
        },
        "RightBrowInner_up" : {
            "x" : 185.8408203125,
            "y" : 521.2518310546875
        },
        "MouthInner_down_left" : {
            "x" : 236.1346435546875,
            "y" : 735.378662109375
        },
        "RightEyeUpperInner" : {
            "x" : 193.2008666992188,
            "y" : 592.6421508789062
        },
        "MouthLeft_corner" : {
            "x" : 284.9378051757812,
            "y" : 746.2679443359375
        },
        "CheekRight" : {
            "x" : 152.3889007568359,
            "y" : 609.35986328125
        },
        "CheekLeft" : {
            "x" : 438.235595703125,
            "y" : 585.3250732421875
        },
        "BaseCenterLeft" : {
            "x" : 229.267333984375,
            "y" : 667.9288330078125
        },
        "CheekRight4" : {
            "x" : 143.7559204101562,
            "y" : 760.3340454101562
        },
        "MouthInner_down_right" : {
            "x" : 190.0480041503906,
            "y" : 740.7373657226562
        },
        "CheekLeft5" : {
            "x" : 368.0408935546875,
            "y" : 831.2899169921875
        },
        "AlaRight2" : {
            "x" : 175.4127044677734,
            "y" : 655.6959228515625
        },
        "MouthLeft_philtrum" : {
            "x" : 218.2729339599609,
            "y" : 713.1187744140625
        },
        "LeftEyePupil" : {
            "x" : 319.5662231445312,
            "y" : 578.82421875
        },
        "LeftBrowOuter_down" : {
            "x" : 365.8623657226562,
            "y" : 529.9217529296875
        },
        "MouthRight_up_2" : {
            "x" : 178.7674713134766,
            "y" : 725.8600463867188
        },
        "Ridge1" : {
            "x" : 212.0185852050781,
            "y" : 588.4854736328125
        },
        "AlaLeft1" : {
            "x" : 255.4401092529297,
            "y" : 629.6630859375
        },
        "CheekRight5" : {
            "x" : 149.5101623535156,
            "y" : 798.6365966796875
        },
        "MouthInner_up_left" : {
            "x" : 236.1982879638672,
            "y" : 735.1634521484375
        },
        "RightEyeLowerInner" : {
            "x" : 194.1966247558594,
            "y" : 605.4564208984375
        },
        "MouthRight_up_1" : {
            "x" : 171.5893402099609,
            "y" : 739.1343994140625
        },
        "CheekRight3" : {
            "x" : 140.9126739501953,
            "y" : 722.362060546875
        },
        "MouthLeft_up_1" : {
            "x" : 265.6402587890625,
            "y" : 729.9022827148438
        },
        "RidgeRoot" : {
            "x" : 222.4519500732422,
            "y" : 566.644775390625
        },
        "RidgeTip" : {
            "x" : 189.9215087890625,
            "y" : 630.741455078125
        },
        "LeftEyeOuterEyeCorner" : {
            "x" : 344.2440795898438,
            "y" : 578.0490112304688
        },
        "AlaRight1" : {
            "x" : 180.1779174804688,
            "y" : 638.1236572265625
        },
        "LeftBrowInner_up" : {
            "x" : 269.3549194335938,
            "y" : 506.4639587402344
        },
        "LeftBrowMiddle_up" : {
            "x" : 321.305908203125,
            "y" : 496.8917541503906
        },
        "RightBrowOuter_up" : {
            "x" : 142.8338928222656,
            "y" : 547.0025634765625
        },
        "MouthInner_up" : {
            "x" : 204.6378936767578,
            "y" : 736.162841796875
        },
        "CheekLeft2" : {
            "x" : 442.5907592773438,
            "y" : 692.83984375
        },
        "RightEyeUpperOuter" : {
            "x" : 172.6929321289062,
            "y" : 594.5371704101562
        },
        "MouthCenter_philtrum" : {
            "x" : 204.4000701904297,
            "y" : 718.3150634765625
        },
        "CheekLeft3" : {
            "x" : 432.9023742675781,
            "y" : 745.934814453125
        }
    }
}