{
    "angles" : [
        -179.22762110209283,
        -19.363731441528202,
        4.447710532841069
    ],
    "landmarks" : {
        "LeftBrowMiddle_down" : {
            "x" : 349.1820068359375,
            "y" : 615.5294189453125
        },
        "Ridge2" : {
            "x" : 248.9200134277344,
            "y" : 697.3809814453125
        },
        "LeftEyeInnerEyeCorner" : {
            "x" : 321.1653442382812,
            "y" : 640.3993530273438
        },
        "MouthRight_down_2" : {
            "x" : 267.8494262695312,
            "y" : 836.8372802734375
        },
        "MouthRight_corner" : {
            "x" : 229.6559600830078,
            "y" : 821.7401733398438
        },
        "BaseLeft" : {
            "x" : 315.5618286132812,
            "y" : 734.4400634765625
        },
        "RightBrowMiddle_down" : {
            "x" : 197.9617004394531,
            "y" : 627.0377807617188
        },
        "RightBrowOuter_down" : {
            "x" : 171.2613525390625,
            "y" : 624.7967529296875
        },
        "CheekLeft1" : {
            "x" : 496.9261474609375,
            "y" : 674.9950561523438
        },
        "CheekRight1" : {
            "x" : 170.1386413574219,
            "y" : 701.3387451171875
        },
        "BaseCenterRight" : {
            "x" : 244.9076843261719,
            "y" : 749.7079467773438
        },
        "LeftEyeLowerOuter" : {
            "x" : 365.7787780761719,
            "y" : 637.84228515625
        },
        "BaseRight" : {
            "x" : 228.6000671386719,
            "y" : 746.8828125
        },
        "CheekRight2" : {
            "x" : 170.6835327148438,
            "y" : 746.8583374023438
        },
        "AlaLeft2" : {
            "x" : 290.017578125,
            "y" : 718.2880249023438
        },
        "LeftEyeUpperInner" : {
            "x" : 340.6319885253906,
            "y" : 638.40283203125
        },
        "RightEyeInnerEyeCorner" : {
            "x" : 239.8787536621094,
            "y" : 645.888427734375
        },
        "LeftEyeUpperOuter" : {
            "x" : 365.7787780761719,
            "y" : 637.84228515625
        },
        "BaseCenter" : {
            "x" : 263.6488647460938,
            "y" : 754.2464599609375
        },
        "RightEyeLowerOuter" : {
            "x" : 205.2118225097656,
            "y" : 651.8599853515625
        },
        "MouthLeft_down_1" : {
            "x" : 348.8582763671875,
            "y" : 811.859375
        },
        "MouthInner_down" : {
            "x" : 282.96533203125,
            "y" : 810.7159423828125
        },
        "RightEyeOuterEyeCorner" : {
            "x" : 191.2015380859375,
            "y" : 650.447509765625
        },
        "RightBrowInner_down" : {
            "x" : 228.6051940917969,
            "y" : 632.31298828125
        },
        "CheekLeft4" : {
            "x" : 475.8343811035156,
            "y" : 832.455810546875
        },
        "MouthRight_philtrum" : {
            "x" : 261.5269165039062,
            "y" : 795.3831176757812
        },
        "MouthRight_down_1" : {
            "x" : 245.2364196777344,
            "y" : 832.9219970703125
        },
        "LeftBrowOuter_up" : {
            "x" : 404.3120422363281,
            "y" : 602.6874389648438
        },
        "CheekRight7" : {
            "x" : 261.0664978027344,
            "y" : 939.669677734375
        },
        "MouthInner_up_right" : {
            "x" : 261.0426330566406,
            "y" : 814.143798828125
        },
        "LeftEyeLowerInner" : {
            "x" : 340.6319885253906,
            "y" : 638.40283203125
        },
        "RightBrowMiddle_up" : {
            "x" : 197.0072479248047,
            "y" : 610.184326171875
        },
        "MouthLeft_down_2" : {
            "x" : 319.1167602539062,
            "y" : 827.1205444335938
        },
        "LeftBrowInner_down" : {
            "x" : 297.0857849121094,
            "y" : 626.7916259765625
        },
        "CheekLeft6" : {
            "x" : 400.9100952148438,
            "y" : 913.4986572265625
        },
        "CheekRight6" : {
            "x" : 233.7029418945312,
            "y" : 909.112060546875
        },
        "MouthLeft_up_2" : {
            "x" : 320.3752136230469,
            "y" : 786.4072265625
        },
        "RightEyePupil" : {
            "x" : 220.8481140136719,
            "y" : 644.3399047851562
        },
        "MouthCenter_lower" : {
            "x" : 288.3140869140625,
            "y" : 836.3402099609375
        },
        "CheekLeft7" : {
            "x" : 353.9903259277344,
            "y" : 940.138671875
        },
        "ChinCenter" : {
            "x" : 300.9476623535156,
            "y" : 951.9910888671875
        },
        "RightBrowInner_up" : {
            "x" : 227.0327453613281,
            "y" : 617.64306640625
        },
        "MouthInner_down_left" : {
            "x" : 317.7029113769531,
            "y" : 801.2110595703125
        },
        "RightEyeUpperInner" : {
            "x" : 226.2033538818359,
            "y" : 643.0829467773438
        },
        "MouthLeft_corner" : {
            "x" : 370.19677734375,
            "y" : 792.5717163085938
        },
        "CheekRight" : {
            "x" : 173.9063262939453,
            "y" : 656.7025146484375
        },
        "CheekLeft" : {
            "x" : 490.061279296875,
            "y" : 624.45947265625
        },
        "BaseCenterLeft" : {
            "x" : 289.4094848632812,
            "y" : 742.8941040039062
        },
        "CheekRight4" : {
            "x" : 194.1093444824219,
            "y" : 832.8192138671875
        },
        "MouthInner_down_right" : {
            "x" : 261.0426330566406,
            "y" : 814.143798828125
        },
        "CheekLeft5" : {
            "x" : 442.5718688964844,
            "y" : 876.02783203125
        },
        "AlaRight2" : {
            "x" : 227.66552734375,
            "y" : 734.4423828125
        },
        "MouthLeft_philtrum" : {
            "x" : 295.7113037109375,
            "y" : 787.8714599609375
        },
        "LeftEyePupil" : {
            "x" : 363.1812744140625,
            "y" : 636.77099609375
        },
        "LeftBrowOuter_down" : {
            "x" : 403.7913818359375,
            "y" : 613.3040771484375
        },
        "MouthRight_up_2" : {
            "x" : 247.6515350341797,
            "y" : 801.1925048828125
        },
        "Ridge1" : {
            "x" : 255.3453979492188,
            "y" : 667.2943115234375
        },
        "AlaLeft1" : {
            "x" : 310.9916381835938,
            "y" : 696.739501953125
        },
        "CheekRight5" : {
            "x" : 211.1600036621094,
            "y" : 871.9468994140625
        },
        "MouthInner_up_left" : {
            "x" : 317.7029113769531,
            "y" : 801.2110595703125
        },
        "RightEyeLowerInner" : {
            "x" : 225.8425598144531,
            "y" : 650.09765625
        },
        "MouthRight_up_1" : {
            "x" : 235.9057312011719,
            "y" : 810.162841796875
        },
        "CheekRight3" : {
            "x" : 181.2452697753906,
            "y" : 790.5205078125
        },
        "MouthLeft_up_1" : {
            "x" : 347.156982421875,
            "y" : 786.7542724609375
        },
        "RidgeRoot" : {
            "x" : 260.6486206054688,
            "y" : 637.9938354492188
        },
        "RidgeTip" : {
            "x" : 244.014404296875,
            "y" : 727.2984619140625
        },
        "LeftEyeOuterEyeCorner" : {
            "x" : 386.7214965820312,
            "y" : 637.595458984375
        },
        "AlaRight1" : {
            "x" : 223.7626953125,
            "y" : 709.5768432617188
        },
        "LeftBrowInner_up" : {
            "x" : 293.2506103515625,
            "y" : 612.0948486328125
        },
        "LeftBrowMiddle_up" : {
            "x" : 346.9818725585938,
            "y" : 596.4363403320312
        },
        "RightBrowOuter_up" : {
            "x" : 170.8938598632812,
            "y" : 612.3687744140625
        },
        "MouthInner_up" : {
            "x" : 282.96533203125,
            "y" : 810.7159423828125
        },
        "CheekLeft2" : {
            "x" : 500.4312438964844,
            "y" : 728.5150146484375
        },
        "RightEyeUpperOuter" : {
            "x" : 205.5099792480469,
            "y" : 644.2587890625
        },
        "MouthCenter_philtrum" : {
            "x" : 279.6341552734375,
            "y" : 796.9286499023438
        },
        "CheekLeft3" : {
            "x" : 496.4440307617188,
            "y" : 782.573486328125
        }
    }
}