{
    "angles" : [
        174.37799776591282,
        0.4310724163063379,
        -2.670741564134729
    ],
    "landmarks" : {
        "LeftBrowMiddle_down" : {
            "x" : 472.3078918457031,
            "y" : 558.150634765625
        },
        "Ridge2" : {
            "x" : 383.0651245117188,
            "y" : 638.2144775390625
        },
        "LeftEyeInnerEyeCorner" : {
            "x" : 425.9713439941406,
            "y" : 600.9034423828125
        },
        "MouthRight_down_2" : {
            "x" : 352.7532958984375,
            "y" : 780.3367309570312
        },
        "MouthRight_corner" : {
            "x" : 307.2280883789062,
            "y" : 760.4212646484375
        },
        "BaseLeft" : {
            "x" : 419.3233642578125,
            "y" : 695.7982177734375
        },
        "RightBrowMiddle_down" : {
            "x" : 299.0673828125,
            "y" : 549.2196044921875
        },
        "RightBrowOuter_down" : {
            "x" : 253.4846801757812,
            "y" : 555.3536987304688
        },
        "CheekLeft1" : {
            "x" : 219.6808166503906,
            "y" : 638.0340576171875
        },
        "CheekRight1" : {
            "x" : 532.96240234375,
            "y" : 651.431396484375
        },
        "BaseCenterRight" : {
            "x" : 358.3558654785156,
            "y" : 693.1644287109375
        },
        "LeftEyeLowerOuter" : {
            "x" : 467.5198364257812,
            "y" : 608.3995361328125
        },
        "BaseRight" : {
            "x" : 338.0990905761719,
            "y" : 692.929443359375
        },
        "CheekRight2" : {
            "x" : 530.5467529296875,
            "y" : 699.1614379882812
        },
        "AlaLeft2" : {
            "x" : 415.6249084472656,
            "y" : 673.4962158203125
        },
        "LeftEyeUpperInner" : {
            "x" : 443.5909729003906,
            "y" : 593.3907470703125
        },
        "RightEyeInnerEyeCorner" : {
            "x" : 341.61181640625,
            "y" : 597.539794921875
        },
        "LeftEyeUpperOuter" : {
            "x" : 467.8222351074219,
            "y" : 594.4042358398438
        },
        "BaseCenter" : {
            "x" : 379.6830444335938,
            "y" : 697.44677734375
        },
        "RightEyeLowerOuter" : {
            "x" : 297.1495971679688,
            "y" : 601.0582275390625
        },
        "MouthLeft_down_1" : {
            "x" : 426.6016235351562,
            "y" : 775.4783935546875
        },
        "MouthInner_down" : {
            "x" : 377.6046142578125,
            "y" : 761.338134765625
        },
        "RightEyeOuterEyeCorner" : {
            "x" : 278.6605224609375,
            "y" : 592.9867553710938
        },
        "RightBrowInner_down" : {
            "x" : 344.8911743164062,
            "y" : 557.9810791015625
        },
        "CheekLeft4" : {
            "x" : 229.4699096679688,
            "y" : 783.687744140625
        },
        "MouthRight_philtrum" : {
            "x" : 360.856689453125,
            "y" : 743.8499755859375
        },
        "MouthRight_down_1" : {
            "x" : 327.1289978027344,
            "y" : 772.9364013671875
        },
        "LeftBrowOuter_up" : {
            "x" : 515.2073974609375,
            "y" : 557.030029296875
        },
        "CheekRight7" : {
            "x" : 416.4307250976562,
            "y" : 888.4361572265625
        },
        "MouthInner_up_right" : {
            "x" : 349.5606079101562,
            "y" : 758.989501953125
        },
        "LeftEyeLowerInner" : {
            "x" : 442.6941528320312,
            "y" : 606.0238037109375
        },
        "RightBrowMiddle_up" : {
            "x" : 298.7680053710938,
            "y" : 528.4339599609375
        },
        "MouthLeft_down_2" : {
            "x" : 401.8815307617188,
            "y" : 781.782958984375
        },
        "LeftBrowInner_down" : {
            "x" : 427.5406799316406,
            "y" : 561.337890625
        },
        "CheekLeft6" : {
            "x" : 284.2280883789062,
            "y" : 860.9293212890625
        },
        "CheekRight6" : {
            "x" : 455.6183776855469,
            "y" : 865.7373046875
        },
        "MouthLeft_up_2" : {
            "x" : 412.3826904296875,
            "y" : 748.844970703125
        },
        "RightEyePupil" : {
            "x" : 309.5283813476562,
            "y" : 591.8717041015625
        },
        "MouthCenter_lower" : {
            "x" : 377.1231079101562,
            "y" : 783.5897216796875
        },
        "CheekLeft7" : {
            "x" : 323.427001953125,
            "y" : 886.1727905273438
        },
        "ChinCenter" : {
            "x" : 370.6697692871094,
            "y" : 895.5418701171875
        },
        "RightBrowInner_up" : {
            "x" : 346.4884033203125,
            "y" : 539.6788940429688
        },
        "MouthInner_down_left" : {
            "x" : 405.492431640625,
            "y" : 760.7215576171875
        },
        "RightEyeUpperInner" : {
            "x" : 324.6563720703125,
            "y" : 588.5838623046875
        },
        "MouthLeft_corner" : {
            "x" : 447.0106506347656,
            "y" : 765.250732421875
        },
        "CheekRight" : {
            "x" : 529.8902587890625,
            "y" : 604.711669921875
        },
        "CheekLeft" : {
            "x" : 226.4481658935547,
            "y" : 590.0838623046875
        },
        "BaseCenterLeft" : {
            "x" : 399.736083984375,
            "y" : 695.691162109375
        },
        "CheekRight4" : {
            "x" : 512.9462890625,
            "y" : 791.9005737304688
        },
        "MouthInner_down_right" : {
            "x" : 349.5606079101562,
            "y" : 758.989501953125
        },
        "CheekLeft5" : {
            "x" : 251.0654296875,
            "y" : 826.58740234375
        },
        "AlaRight2" : {
            "x" : 345.2264404296875,
            "y" : 669.4166259765625
        },
        "MouthLeft_philtrum" : {
            "x" : 395.1485595703125,
            "y" : 744.4024658203125
        },
        "LeftEyePupil" : {
            "x" : 457.5286254882812,
            "y" : 599.293212890625
        },
        "LeftBrowOuter_down" : {
            "x" : 514.0264282226562,
            "y" : 568.8051147460938
        },
        "MouthRight_up_2" : {
            "x" : 342.8147583007812,
            "y" : 746.912109375
        },
        "Ridge1" : {
            "x" : 384.1246337890625,
            "y" : 609.4519653320312
        },
        "AlaLeft1" : {
            "x" : 422.0094604492188,
            "y" : 658.175537109375
        },
        "CheekRight5" : {
            "x" : 490.032470703125,
            "y" : 832.840087890625
        },
        "MouthInner_up_left" : {
            "x" : 405.492431640625,
            "y" : 760.7215576171875
        },
        "RightEyeLowerInner" : {
            "x" : 323.368896484375,
            "y" : 601.471923828125
        },
        "MouthRight_up_1" : {
            "x" : 323.9423828125,
            "y" : 752.26220703125
        },
        "CheekRight3" : {
            "x" : 525.3790893554688,
            "y" : 746.2389526367188
        },
        "MouthLeft_up_1" : {
            "x" : 431.084228515625,
            "y" : 754.679931640625
        },
        "RidgeRoot" : {
            "x" : 385.3955688476562,
            "y" : 581.6962890625
        },
        "RidgeTip" : {
            "x" : 380.88330078125,
            "y" : 665.2275390625
        },
        "LeftEyeOuterEyeCorner" : {
            "x" : 486.1396484375,
            "y" : 603.2197265625
        },
        "AlaRight1" : {
            "x" : 340.4124145507812,
            "y" : 653.7241821289062
        },
        "LeftBrowInner_up" : {
            "x" : 427.6630859375,
            "y" : 545.7052001953125
        },
        "LeftBrowMiddle_up" : {
            "x" : 473.5907897949219,
            "y" : 538.1217041015625
        },
        "RightBrowOuter_up" : {
            "x" : 252.8468017578125,
            "y" : 543.4308471679688
        },
        "MouthInner_up" : {
            "x" : 377.6046142578125,
            "y" : 761.338134765625
        },
        "CheekLeft2" : {
            "x" : 216.2485198974609,
            "y" : 687.522705078125
        },
        "RightEyeUpperOuter" : {
            "x" : 298.4022827148438,
            "y" : 586.0345458984375
        },
        "MouthCenter_philtrum" : {
            "x" : 378.4821472167969,
            "y" : 748.5164794921875
        },
        "CheekLeft3" : {
            "x" : 220.1432495117188,
            "y" : 735.7152099609375
        }
    }
}